setup.cfg
setup.py
schemata/__init__.py
schemata.egg-info/PKG-INFO
schemata.egg-info/SOURCES.txt
schemata.egg-info/dependency_links.txt
schemata.egg-info/entry_points.txt
schemata.egg-info/top_level.txt
schemata.egg-info/zip-safe