Metadata-Version: 1.0
Name: schemata
Version: 0.0
Summary: Schema Validation and Conversion
Home-page: UNKNOWN
Author: Chris Perkins
Author-email: chris@percious.com
License: MIT
Keywords: schema,validation
Platform: UNKNOWN
